metronome_pulse_sqlite/__init__.py
metronome_pulse_sqlite/connector.py
metronome_pulse_sqlite/readonly_connector.py
metronome_pulse_sqlite/writeonly_connector.py
metronome_pulse_sqlite-0.1.0.dist-info/METADATA
metronome_pulse_sqlite-0.1.0.dist-info/WHEEL
metronome_pulse_sqlite-0.1.0.dist-info/licenses/LICENSE
metronome_pulse_sqlite-0.1.0.dist-info/RECORD
