Metadata-Version: 2.4
Name: metronome-pulse-sqlite
Version: 0.1.0
Summary: High-performance SQLite connector for DataPulse - async-first, local storage, and development features
Project-URL: Homepage, https://github.com/datametronome/metronome-pulse-sqlite
Project-URL: Repository, https://github.com/datametronome/metronome-pulse-sqlite
Project-URL: Documentation, https://datametronome.dev/docs/pulse-sqlite
Project-URL: Issues, https://github.com/datametronome/metronome-pulse-sqlite/issues
Project-URL: Changelog, https://github.com/datametronome/metronome-pulse-sqlite/blob/main/CHANGELOG.md
Project-URL: Download, https://pypi.org/project/metronome-pulse-sqlite/#files
Author-email: DataMetronome Team <team@datametronome.dev>
Maintainer-email: DataMetronome Team <team@datametronome.dev>
License: MIT
License-File: LICENSE
Keywords: async,connector,data-pipeline,data-quality,database,etl,local-storage,sqlite
Classifier: Development Status :: 4 - Beta
Classifier: Framework :: AsyncIO
Classifier: Intended Audience :: Developers
Classifier: License :: OSI Approved :: MIT License
Classifier: Operating System :: OS Independent
Classifier: Programming Language :: Python :: 3
Classifier: Programming Language :: Python :: 3.9
Classifier: Programming Language :: Python :: 3.10
Classifier: Programming Language :: Python :: 3.11
Classifier: Programming Language :: Python :: 3.12
Classifier: Programming Language :: Python :: 3.13
Classifier: Topic :: Database
Classifier: Topic :: Software Development :: Libraries :: Python Modules
Classifier: Typing :: Typed
Requires-Python: >=3.9
Requires-Dist: metronome-pulse-core>=0.1.0
Requires-Dist: pydantic>=2.0.0
Requires-Dist: typing-extensions>=4.0.0; python_version < '3.12'
Provides-Extra: dev
Requires-Dist: black>=23.0.0; extra == 'dev'
Requires-Dist: isort>=5.12.0; extra == 'dev'
Requires-Dist: mypy>=1.0.0; extra == 'dev'
Requires-Dist: pre-commit>=3.0.0; extra == 'dev'
Requires-Dist: pytest-asyncio>=0.21.0; extra == 'dev'
Requires-Dist: pytest-benchmark>=4.0.0; extra == 'dev'
Requires-Dist: pytest-cov>=4.0.0; extra == 'dev'
Requires-Dist: pytest-mock>=3.10.0; extra == 'dev'
Requires-Dist: pytest>=7.0.0; extra == 'dev'
Requires-Dist: ruff>=0.1.0; extra == 'dev'
Provides-Extra: docs
Requires-Dist: myst-parser>=2.0.0; extra == 'docs'
Requires-Dist: sphinx-rtd-theme>=1.3.0; extra == 'docs'
Requires-Dist: sphinx>=7.0.0; extra == 'docs'
Provides-Extra: performance
Requires-Dist: memory-profiler>=0.61.0; extra == 'performance'
Requires-Dist: psutil>=5.9.0; extra == 'performance'
Requires-Dist: pytest-benchmark>=4.0.0; extra == 'performance'
Provides-Extra: test
Requires-Dist: pytest-asyncio>=0.21.0; extra == 'test'
Requires-Dist: pytest-benchmark>=4.0.0; extra == 'test'
Requires-Dist: pytest-cov>=4.0.0; extra == 'test'
Requires-Dist: pytest-mock>=3.10.0; extra == 'test'
Requires-Dist: pytest>=7.0.0; extra == 'test'
